pysourcesfetcher/__init__.py
pysourcesfetcher/cli.py
pysourcesfetcher/pysourcesfetcher.py
pysourcesfetcher-0.1.0.dist-info/AUTHORS.rst
pysourcesfetcher-0.1.0.dist-info/LICENSE
pysourcesfetcher-0.1.0.dist-info/METADATA
pysourcesfetcher-0.1.0.dist-info/WHEEL
pysourcesfetcher-0.1.0.dist-info/entry_points.txt
pysourcesfetcher-0.1.0.dist-info/top_level.txt
pysourcesfetcher-0.1.0.dist-info/RECORD
