Metadata-Version: 2.1
Name: pysourcesfetcher
Version: 0.1.0
Summary: Python3 module and cli tool to retrieve useful info from sources code in various languages.
Home-page: https://github.com/weallfloatdownhere/pysourcesfetcher
Author: pysourcesfetcher
Author-email: noreply@local.lab
License: MIT license
Keywords: pysourcesfetcher
Classifier: Development Status :: 2 - Pre-Alpha
Classifier: Intended Audience :: Developers
Classifier: License :: OSI Approved :: MIT License
Classifier: Natural Language :: English
Classifier: Programming Language :: Python :: 3
Classifier: Programming Language :: Python :: 3.6
Classifier: Programming Language :: Python :: 3.7
Classifier: Programming Language :: Python :: 3.8
Requires-Python: >=3.6
License-File: LICENSE
License-File: AUTHORS.rst
Requires-Dist: fire (==0.4.0)
Requires-Dist: omegaconf (==2.2.2)
Requires-Dist: ripgrepy (==1.1.0)
